{
  "results": [
    [
      "absent",
      "absent",
      "absent",
      "absent",
      "absent"
    ],
    [
      "present",
      "correct",
      "absent",
      "absent",
      "absent"
    ],
    [
      "absent",
      "correct",
      "correct",
      "correct",
      "correct"
    ],
    [
      "correct",
      "correct",
      "correct",
      "correct",
      "correct"
    ]
  ],
  "enrichedResults": [
    {
      "lineStatuses": [
        "absent",
        "absent",
        "absent",
        "absent",
        "absent"
      ],
      "lineEmoji": [
        "拘勇",
        "拘勇",
        "拘勇",
        "拘勇",
        "拘勇"
      ],
      "lineProgress": 0,
      "lineScore": 10
    },
    {
      "lineStatuses": [
        "present",
        "correct",
        "absent",
        "absent",
        "absent"
      ],
      "lineEmoji": [
        "游릳",
        "游릴",
        "拘勇",
        "拘勇",
        "拘勇"
      ],
      "lineProgress": 3,
      "lineScore": 7
    },
    {
      "lineStatuses": [
        "absent",
        "correct",
        "correct",
        "correct",
        "correct"
      ],
      "lineEmoji": [
        "拘勇",
        "游릴",
        "游릴",
        "游릴",
        "游릴"
      ],
      "lineProgress": 8,
      "lineScore": 2
    },
    {
      "lineStatuses": [
        "correct",
        "correct",
        "correct",
        "correct",
        "correct"
      ],
      "lineEmoji": [
        "游릴",
        "游릴",
        "游릴",
        "游릴",
        "游릴"
      ],
      "lineProgress": 10,
      "lineScore": 0
    }
  ],
  "puzzleScore": 19,
  "puzzleNum": 743,
  "puzzleDate": "2023-07-02",
  "guessCount": 4,
  "isHardMode": true,
  "playerName": "nancy",
  "timestamp": "7/2/2023 8:51:18",
  "rawShare": "Wordle 743 4/6*\n\n拘럭샢拘럭샢拘\n游릳游릴拘럭샢拘\n拘럻릴游릴游릴游릴\n游릴游릴游릴游릴游릴",
  "words": [
    "sound",
    "bossy"
  ],
  "comment": ""
}