{
  "results": [
    [
      "correct",
      "present",
      "absent",
      "absent",
      "absent"
    ],
    [
      "correct",
      "absent",
      "present",
      "present",
      "absent"
    ],
    [
      "correct",
      "absent",
      "present",
      "correct",
      "absent"
    ],
    [
      "correct",
      "correct",
      "correct",
      "correct",
      "correct"
    ]
  ],
  "enrichedResults": [
    {
      "lineStatuses": [
        "correct",
        "present",
        "absent",
        "absent",
        "absent"
      ],
      "lineEmoji": [
        "游릴",
        "游릳",
        "拘勇",
        "拘勇",
        "拘勇"
      ],
      "lineProgress": 3,
      "lineScore": 7
    },
    {
      "lineStatuses": [
        "correct",
        "absent",
        "present",
        "present",
        "absent"
      ],
      "lineEmoji": [
        "游릴",
        "拘勇",
        "游릳",
        "游릳",
        "拘勇"
      ],
      "lineProgress": 4,
      "lineScore": 6
    },
    {
      "lineStatuses": [
        "correct",
        "absent",
        "present",
        "correct",
        "absent"
      ],
      "lineEmoji": [
        "游릴",
        "拘勇",
        "游릳",
        "游릴",
        "拘勇"
      ],
      "lineProgress": 5,
      "lineScore": 5
    },
    {
      "lineStatuses": [
        "correct",
        "correct",
        "correct",
        "correct",
        "correct"
      ],
      "lineEmoji": [
        "游릴",
        "游릴",
        "游릴",
        "游릴",
        "游릴"
      ],
      "lineProgress": 10,
      "lineScore": 0
    }
  ],
  "puzzleScore": 18,
  "puzzleNum": 760,
  "puzzleDate": "2023-07-19",
  "guessCount": 4,
  "isHardMode": true,
  "playerName": "mandy",
  "timestamp": "7/19/2023 6:58:42",
  "rawShare": "Wordle 760 4/6*\n\n游릴游릳拘럭샢拘\n游릴拘럻릳游릳拘\n游릴拘럻릳游릴拘\n游릴游릴游릴游릴游릴",
  "words": [
    "thick",
    "tacit"
  ],
  "comment": ""
}