{
  "results": [
    [
      "absent",
      "absent",
      "present",
      "absent",
      "present"
    ],
    [
      "present",
      "present",
      "present",
      "absent",
      "absent"
    ],
    [
      "correct",
      "present",
      "present",
      "absent",
      "correct"
    ],
    [
      "correct",
      "correct",
      "correct",
      "correct",
      "correct"
    ]
  ],
  "enrichedResults": [
    {
      "lineStatuses": [
        "absent",
        "absent",
        "present",
        "absent",
        "present"
      ],
      "lineEmoji": [
        "拘勇",
        "拘勇",
        "游릳",
        "拘勇",
        "游릳"
      ],
      "lineProgress": 2,
      "lineScore": 8
    },
    {
      "lineStatuses": [
        "present",
        "present",
        "present",
        "absent",
        "absent"
      ],
      "lineEmoji": [
        "游릳",
        "游릳",
        "游릳",
        "拘勇",
        "拘勇"
      ],
      "lineProgress": 3,
      "lineScore": 7
    },
    {
      "lineStatuses": [
        "correct",
        "present",
        "present",
        "absent",
        "correct"
      ],
      "lineEmoji": [
        "游릴",
        "游릳",
        "游릳",
        "拘勇",
        "游릴"
      ],
      "lineProgress": 6,
      "lineScore": 4
    },
    {
      "lineStatuses": [
        "correct",
        "correct",
        "correct",
        "correct",
        "correct"
      ],
      "lineEmoji": [
        "游릴",
        "游릴",
        "游릴",
        "游릴",
        "游릴"
      ],
      "lineProgress": 10,
      "lineScore": 0
    }
  ],
  "puzzleScore": 19,
  "puzzleNum": 711,
  "puzzleDate": "2023-05-31",
  "guessCount": 4,
  "isHardMode": true,
  "playerName": "lindsay",
  "timestamp": "5/31/2023 5:32:00",
  "rawShare": "Wordle 711 4/6*\n\n拘럭샢游릳拘럻릳\n游릳游릳游릳拘럭샢\n游릴游릳游릳拘럻릴\n游릴游릴游릴游릴游릴",
  "words": [
    "leash",
    "algae"
  ]
}