{
  "results": [
    [
      "absent",
      "absent",
      "absent",
      "present",
      "present"
    ],
    [
      "correct",
      "correct",
      "correct",
      "correct",
      "correct"
    ]
  ],
  "enrichedResults": [
    {
      "lineStatuses": [
        "absent",
        "absent",
        "absent",
        "present",
        "present"
      ],
      "lineEmoji": [
        "拘勇",
        "拘勇",
        "拘勇",
        "游릳",
        "游릳"
      ],
      "lineProgress": 2,
      "lineScore": 8
    },
    {
      "lineStatuses": [
        "correct",
        "correct",
        "correct",
        "correct",
        "correct"
      ],
      "lineEmoji": [
        "游릴",
        "游릴",
        "游릴",
        "游릴",
        "游릴"
      ],
      "lineProgress": 10,
      "lineScore": 0
    }
  ],
  "puzzleScore": 8,
  "puzzleNum": 671,
  "puzzleDate": "2023-04-21",
  "guessCount": 2,
  "isHardMode": true,
  "playerName": "fred",
  "timestamp": "4/21/2023 6:14:08",
  "rawShare": "Wordle 671 2/6*\n\n拘럭샢拘럻릳游릳\n游릴游릴游릴游릴游릴",
  "words": [],
  "comment": ""
}