{
  "results": [
    [
      "absent",
      "absent",
      "absent",
      "present",
      "present"
    ],
    [
      "absent",
      "correct",
      "absent",
      "absent",
      "correct"
    ],
    [
      "absent",
      "correct",
      "correct",
      "correct",
      "correct"
    ],
    [
      "correct",
      "correct",
      "correct",
      "correct",
      "correct"
    ]
  ],
  "enrichedResults": [
    {
      "lineStatuses": [
        "absent",
        "absent",
        "absent",
        "present",
        "present"
      ],
      "lineEmoji": [
        "拘勇",
        "拘勇",
        "拘勇",
        "游릳",
        "游릳"
      ],
      "lineProgress": 2,
      "lineScore": 8
    },
    {
      "lineStatuses": [
        "absent",
        "correct",
        "absent",
        "absent",
        "correct"
      ],
      "lineEmoji": [
        "拘勇",
        "游릴",
        "拘勇",
        "拘勇",
        "游릴"
      ],
      "lineProgress": 4,
      "lineScore": 6
    },
    {
      "lineStatuses": [
        "absent",
        "correct",
        "correct",
        "correct",
        "correct"
      ],
      "lineEmoji": [
        "拘勇",
        "游릴",
        "游릴",
        "游릴",
        "游릴"
      ],
      "lineProgress": 8,
      "lineScore": 2
    },
    {
      "lineStatuses": [
        "correct",
        "correct",
        "correct",
        "correct",
        "correct"
      ],
      "lineEmoji": [
        "游릴",
        "游릴",
        "游릴",
        "游릴",
        "游릴"
      ],
      "lineProgress": 10,
      "lineScore": 0
    }
  ],
  "puzzleScore": 16,
  "puzzleNum": 756,
  "puzzleDate": "2023-07-15",
  "guessCount": 4,
  "isHardMode": true,
  "playerName": "mandy",
  "timestamp": "7/15/2023 9:11:07",
  "rawShare": "Wordle 756 4/6*\n\n拘럭샢拘럻릳游릳\n拘럻릴拘럭샢游릴\n拘럻릴游릴游릴游릴\n游릴游릴游릴游릴游릴",
  "words": [
    "brake",
    "drone"
  ],
  "comment": ""
}